Metadata-Version: 2.1
Name: python-strategies-breezeconnect
Version: 2.0
Summary: breeze connect strategies in python
Home-page: https://github.com/pypa/sampleproject
Author: UAT python strategy Breeze Connect
Author-email: test@mail.com
License: UNKNOWN
Platform: UNKNOWN
Classifier: Programming Language :: Python :: 3
Classifier: License :: OSI Approved :: MIT License
Classifier: Operating System :: OS Independent
Requires-Python: >=3.6
License-File: LICENSE
